NEMO_billing/__init__.py
NEMO_billing/admin.py
NEMO_billing/api.py
NEMO_billing/app_settings.py
NEMO_billing/apps.py
NEMO_billing/customization.py
NEMO_billing/exceptions.py
NEMO_billing/models.py
NEMO_billing/pdf_utilities.py
NEMO_billing/policy.py
NEMO_billing/urls.py
NEMO_billing/utilities.py
NEMO_billing/views.py
NEMO_billing/cap_discount/__init__.py
NEMO_billing/cap_discount/admin.py
NEMO_billing/cap_discount/app_settings.py
NEMO_billing/cap_discount/apps.py
NEMO_billing/cap_discount/customization.py
NEMO_billing/cap_discount/exceptions.py
NEMO_billing/cap_discount/models.py
NEMO_billing/cap_discount/processors.py
NEMO_billing/cap_discount/urls.py
NEMO_billing/cap_discount/views.py
NEMO_billing/cap_discount/migrations/0001_initial.py
NEMO_billing/cap_discount/migrations/0002_version_2_0_0.py
NEMO_billing/cap_discount/migrations/0003_multi_tier_discount.py
NEMO_billing/cap_discount/migrations/0004_shortened_unique_constraints.py
NEMO_billing/cap_discount/migrations/0005_cap_multi_core_facilities.py
NEMO_billing/cap_discount/migrations/0006_capdiscount_creation_time_and_more.py
NEMO_billing/cap_discount/migrations/0007_alter_capdiscount_options.py
NEMO_billing/cap_discount/migrations/__init__.py
NEMO_billing/cap_discount/templates/cap_discount/cap_discount_status.html
NEMO_billing/cap_discount/templates/cap_discount/usage_cap_discounts.html
NEMO_billing/cap_discount/templates/customizations/customizations_cap_discount.html
NEMO_billing/invoices/__init__.py
NEMO_billing/invoices/admin.py
NEMO_billing/invoices/api.py
NEMO_billing/invoices/app_settings.py
NEMO_billing/invoices/apps.py
NEMO_billing/invoices/customization.py
NEMO_billing/invoices/exceptions.py
NEMO_billing/invoices/models.py
NEMO_billing/invoices/processors.py
NEMO_billing/invoices/renderers.py
NEMO_billing/invoices/urls.py
NEMO_billing/invoices/utilities.py
NEMO_billing/invoices/management/__init__.py
NEMO_billing/invoices/management/commands/__init__.py
nemo_billing-4.7.0.dist-info/licenses/LICENSE
nemo_billing-4.7.0.dist-info/METADATA
nemo_billing-4.7.0.dist-info/WHEEL
nemo_billing-4.7.0.dist-info/top_level.txt
nemo_billing-4.7.0.dist-info/RECORD
