Metadata-Version: 2.4
Name: NEMO-billing
Version: 4.7.0
Summary: Billing plugin for NEMO
Author-email: Atlantis Labs LLC <atlantis@atlantislabs.io>
License: MIT License
Project-URL: Homepage, https://gitlab.com/nemo-community/atlantis-labs/nemo-billing
Project-URL: Changelog, https://gitlab.com/nemo-community/atlantis-labs/nemo-billing/-/releases
Project-URL: Issues, https://gitlab.com/nemo-community/atlantis-labs/nemo-billing/-/issues
Project-URL: CI, https://gitlab.com/nemo-community/atlantis-labs/nemo-billing/-/pipelines
Keywords: NEMO
Classifier: Development Status :: 5 - Production/Stable
Classifier: Intended Audience :: Developers
Classifier: License :: OSI Approved :: MIT License
Classifier: Framework :: Django :: 4.2
Classifier: Programming Language :: Python :: 3.10
Classifier: Programming Language :: Python :: 3.11
Classifier: Programming Language :: Python :: 3.12
Classifier: Programming Language :: Python :: 3.13
Requires-Python: >=3.10
License-File: LICENSE
Requires-Dist: django
Requires-Dist: reportlab==4.0.9
Requires-Dist: python-dateutil
Requires-Dist: djangorestframework
Requires-Dist: drf-excel
Provides-Extra: nemo-ce
Requires-Dist: NEMO-CE>=7.3.5; extra == "nemo-ce"
Provides-Extra: nemo
Requires-Dist: NEMO>=7.3.3; extra == "nemo"
Provides-Extra: dev-tools
Requires-Dist: pre-commit; extra == "dev-tools"
Requires-Dist: djlint; extra == "dev-tools"
Requires-Dist: black; extra == "dev-tools"
Dynamic: license-file
